discord/__init__.py
discord/__main__.py
discord/abc.py
discord/activity.py
discord/app_commands.py
discord/appinfo.py
discord/asset.py
discord/audit_logs.py
discord/backoff.py
discord/channel.py
discord/client.py
discord/colour.py
discord/components.py
discord/context_managers.py
discord/custom_warnings.py
discord/embeds.py
discord/emoji.py
discord/enums.py
discord/errors.py
discord/file.py
discord/flags.py
discord/gateway.py
discord/guild.py
discord/guild_scheduled_event.py
discord/http.py
discord/integrations.py
discord/invite.py
discord/iterators.py
discord/member.py
discord/mentions.py
discord/message.py
discord/mixins.py
discord/object.py
discord/oggparse.py
discord/opus.py
discord/partial_emoji.py
discord/permissions.py
discord/player.py
discord/py.typed
discord/raw_models.py
discord/reaction.py
discord/role.py
discord/shard.py
discord/stage_instance.py
discord/state.py
discord/sticker.py
discord/team.py
discord/template.py
discord/threads.py
discord/user.py
discord/utils.py
discord/voice_client.py
discord/widget.py
discord/ext/commands/__init__.py
discord/ext/commands/_types.py
discord/ext/commands/base_core.py
discord/ext/commands/bot.py
discord/ext/commands/bot_base.py
discord/ext/commands/cog.py
discord/ext/commands/common_bot_base.py
discord/ext/commands/context.py
discord/ext/commands/converter.py
discord/ext/commands/cooldowns.py
discord/ext/commands/core.py
discord/ext/commands/ctx_menus_core.py
discord/ext/commands/errors.py
discord/ext/commands/flags.py
discord/ext/commands/help.py
discord/ext/commands/interaction_bot_base.py
discord/ext/commands/params.py
discord/ext/commands/slash_core.py
discord/ext/commands/view.py
discord/ext/tasks/__init__.py
discord/interactions/__init__.py
discord/interactions/application_command.py
discord/interactions/base.py
discord/interactions/message.py
discord/types/__init__.py
discord/types/activity.py
discord/types/appinfo.py
discord/types/audit_log.py
discord/types/channel.py
discord/types/components.py
discord_disnake-2.3.0.2.post0.dist-info/METADATA
discord_disnake-2.3.0.2.post0.dist-info/WHEEL
discord_disnake-2.3.0.2.post0.dist-info/top_level.txt
discord_disnake-2.3.0.2.post0.dist-info/RECORD
