Metadata-Version: 2.1
Name: discord-disnake
Version: 2.3.0.2.post0
Summary: A shim for disnake (Python wrapper for the Discord API)
Home-page: https://github.com/DisnakeDev/discord-disnake
Author: Rapptz, EQUENOS
License: MIT
Project-URL: Documentation, https://docs.disnake.dev/en/latest
Project-URL: Issue tracker, https://github.com/DisnakeDev/discord-disnake/issues
Classifier: Development Status :: 7 - Inactive
Classifier: License :: OSI Approved :: MIT License
Classifier: Intended Audience :: Developers
Classifier: Natural Language :: English
Classifier: Operating System :: OS Independent
Classifier: Programming Language :: Python :: 3.8
Classifier: Programming Language :: Python :: 3.9
Classifier: Programming Language :: Python :: 3.10
Classifier: Topic :: Internet
Classifier: Topic :: Software Development :: Libraries
Classifier: Topic :: Software Development :: Libraries :: Python Modules
Classifier: Topic :: Utilities
Classifier: Typing :: Typed
Requires-Python: >=3.8.0
Requires-Dist: disnake ==2.3.0
